neuralblocks/__init__.py
neuralblocks/py.typed
neuralblocks/configs/__init__.py
neuralblocks/datasets/__init__.py
neuralblocks/evaluation/__init__.py
neuralblocks/models/__init__.py
neuralblocks/schedulers/__init__.py
neuralblocks/training/__init__.py
neuralblocks-0.1.0.dist-info/METADATA
neuralblocks-0.1.0.dist-info/WHEEL
neuralblocks-0.1.0.dist-info/RECORD
