Metadata-Version: 2.3
Name: neuralblocks
Version: 0.1.0
Summary: Reusable components for neural network training, bloat free.
Author-email: Mauro Sciancalepore <maurosciancalepore98@gmail.com>
Requires-Python: >=3.11
Requires-Dist: datasets>=3.2.0
Requires-Dist: matplotlib>=3.10.0
Requires-Dist: opencv-python-headless>=4.10.0.84
Requires-Dist: pandas>=2.2.3
Requires-Dist: pillow>=11.0.0
Requires-Dist: pydantic>=2.10.3
Requires-Dist: torch>=2.5.1
Requires-Dist: torchvision>=0.20.1
